ayrun_pyrps/__init__.py
ayrun_pyrps/components/__init__.py
ayrun_pyrps/components/gameplay.py
ayrun_pyrps/components/menu.py
ayrun_pyrps/components/stats.py
ayrun_pyrps/data/__init__.py
ayrun_pyrps/data/data.json
ayrun_pyrps/data/jsonio.py
ayrun_pyrps/data/types.py
ayrun_pyrps/main.py
LICENSE
ayrun_pyrps-0.1.0.dist-info/entry_points.txt
ayrun_pyrps-0.1.0.dist-info/LICENSE
ayrun_pyrps-0.1.0.dist-info/METADATA
ayrun_pyrps-0.1.0.dist-info/WHEEL
ayrun_pyrps-0.1.0.dist-info/RECORD
