Metadata-Version: 2.1
Name: ayrun-pyrps
Version: 0.1.0
Summary: Instantly play rock-paper-scissors with a simple CLI interface ⚔️
Home-page: https://github.com/ayrun3412/PyRPS
License: MIT
Keywords: rps,cli
Author: ayrun
Author-email: ayrun3412@gmail.com
Requires-Python: >=3.12,<4.0
Classifier: Environment :: Console
Classifier: License :: OSI Approved :: MIT License
Classifier: Operating System :: OS Independent
Classifier: Programming Language :: Python :: 3
Classifier: Programming Language :: Python :: 3.12
Requires-Dist: inquirerpy (>=0.3.4,<0.4.0)
Requires-Dist: rich (>=13.7.1,<14.0.0)
Project-URL: Repository, https://github.com/ayrun3412/PyRPS
